quick_datalog/__init__.py
quick_datalog/asynclog.py
quick_datalog/core.py
quick_datalog-0.2.0.dist-info/licenses/LICENSE
quick_datalog-0.2.0.dist-info/METADATA
quick_datalog-0.2.0.dist-info/WHEEL
quick_datalog-0.2.0.dist-info/top_level.txt
quick_datalog-0.2.0.dist-info/RECORD
