Metadata-Version: 2.4
Name: quick_datalog
Version: 0.2.0
Summary: A lightweight colorful log module with exception capture
Author: huyuenshen
Author-email: huyuenshen@163.com
License: MIT
Classifier: Programming Language :: Python :: 3
Classifier: Operating System :: OS Independent
Requires-Python: >=3.7
License-File: LICENSE
Dynamic: license-file
